MANIFEST.in
README.rst
setup.cfg
setup.py
xylib.i
xylib.py
xylib/bruker_raw.cpp
xylib/bruker_raw.h
xylib/bruker_spc.cpp
xylib/bruker_spc.h
xylib/cache.cpp
xylib/cache.h
xylib/canberra_cnf.cpp
xylib/canberra_cnf.h
xylib/canberra_mca.cpp
xylib/canberra_mca.h
xylib/chiplot.cpp
xylib/chiplot.h
xylib/cpi.cpp
xylib/cpi.h
xylib/csv.cpp
xylib/csv.h
xylib/dbws.cpp
xylib/dbws.h
xylib/pdcif.cpp
xylib/pdcif.h
xylib/philips_raw.cpp
xylib/philips_raw.h
xylib/philips_udf.cpp
xylib/philips_udf.h
xylib/riet7.cpp
xylib/riet7.h
xylib/rigaku_dat.cpp
xylib/rigaku_dat.h
xylib/specsxy.cpp
xylib/specsxy.h
xylib/spectra.cpp
xylib/spectra.h
xylib/text.cpp
xylib/text.h
xylib/util.cpp
xylib/util.h
xylib/uxd.cpp
xylib/uxd.h
xylib/vamas.cpp
xylib/vamas.h
xylib/winspec_spe.cpp
xylib/winspec_spe.h
xylib/xfit_xdd.cpp
xylib/xfit_xdd.h
xylib/xrdml.cpp
xylib/xrdml.h
xylib/xsyg.cpp
xylib/xsyg.h
xylib/xylib.cpp
xylib/xylib.h
xylib_py_fixed_RawV4.egg-info/PKG-INFO
xylib_py_fixed_RawV4.egg-info/SOURCES.txt
xylib_py_fixed_RawV4.egg-info/dependency_links.txt
xylib_py_fixed_RawV4.egg-info/top_level.txt